dsp_utils/__init__.py
dsp_utils/filters/__init__.py
dsp_utils/filters/frequency.py
dsp_utils/signals/__init__.py
dsp_utils/signals/generator.py
dsp_utils/signals/visualizations.py
dsp_utils-0.2.dist-info/METADATA
dsp_utils-0.2.dist-info/WHEEL
dsp_utils-0.2.dist-info/top_level.txt
dsp_utils-0.2.dist-info/RECORD
