Metadata-Version: 2.1
Name: dsp-utils
Version: 0.2
Summary: DSP
Author-email: Yeison Cardona <yencardonaal@unal.edu.co>
Maintainer-email: Yeison Cardona <yencardonaal@unal.edu.co>
License: BSD-2-Clause
Project-URL: Repository, https://github.com/yeisoncardona/python-dsp
Classifier: Development Status :: 3 - Alpha
Classifier: Environment :: Console
Classifier: Intended Audience :: Developers
Classifier: Intended Audience :: Science/Research
Classifier: License :: OSI Approved :: BSD License
Classifier: Natural Language :: English
Classifier: Operating System :: OS Independent
Classifier: Programming Language :: Python
Classifier: Programming Language :: Python :: 3.8
Classifier: Programming Language :: Python :: 3.9
Classifier: Programming Language :: Python :: 3.10
Classifier: Programming Language :: Python :: 3.11
Classifier: Programming Language :: Python :: 3.12
Classifier: Topic :: Software Development :: Libraries :: Python Modules
Requires-Python: >=3.8
Requires-Dist: matplotlib
Requires-Dist: numpy
Requires-Dist: scipy
Requires-Dist: seaborn
Requires-Dist: PyWavelets
Provides-Extra: dev
Provides-Extra: docs
Provides-Extra: security
